README.md
setup.py
pyanoboard/__init__.py
pyanoboard/__main__.py
pyanoboard/config.py
pyanoboard/debug.py
pyanoboard/emulator.py
pyanoboard/key_events.py
pyanoboard/key_handling.py
pyanoboard/keys.py
pyanoboard/midi.py
pyanoboard/pyanoboard.py
pyanoboard.egg-info/PKG-INFO
pyanoboard.egg-info/SOURCES.txt
pyanoboard.egg-info/dependency_links.txt
pyanoboard.egg-info/requires.txt
pyanoboard.egg-info/top_level.txt