Metadata-Version: 2.1
Name: pyanoboard
Version: 1.1.0
Summary: Pyanoboard is a simple piano to keyboard emulator, allowing you to use any MIDI enabled device as a virtual keyboard.
Home-page: https://github.com/QFSW/Pyanoboard
Author: QFSW
Author-email: support@qfsw.co.uk
License: MIT
Platform: UNKNOWN
